LICENSE
README.md
setup.py
felix_fib_py/__init__.py
felix_fib_py/version.py
felix_fib_py.egg-info/PKG-INFO
felix_fib_py.egg-info/SOURCES.txt
felix_fib_py.egg-info/dependency_links.txt
felix_fib_py.egg-info/entry_points.txt
felix_fib_py.egg-info/requires.txt
felix_fib_py.egg-info/top_level.txt
felix_fib_py/cmd/__init__.py
felix_fib_py/cmd/fib_numb.py
felix_fib_py/fib_calcs/__init__.py
felix_fib_py/fib_calcs/fib_number.py
felix_fib_py/fib_calcs/fib_numbers.py
tests/felix_fib_py/__init__.py
tests/felix_fib_py/fib_calcs/__init__.py
tests/felix_fib_py/fib_calcs/test_fib_number.py
tests/felix_fib_py/fib_calcs/test_fib_numbers.py