Metadata-Version: 2.1
Name: felix-fib-py
Version: 0.0.2
Summary: Calculates a Fibonacci number
Home-page: https://github.com/CodeTalks/felix-fib-py
Author: Felix
Author-email: 417055+CodeTalks@users.noreply.github.com
License: UNKNOWN
Platform: UNKNOWN
Classifier: Development Status :: 4 - Beta
Classifier: Programming Language :: Python :: 3
Classifier: Operating System :: OS Independent
Requires-Python: >=3
Provides-Extra: server
License-File: LICENSE
